Metadata-Version: 2.4
Name: 77-MyFirst_HW-Library-77_2025
Version: 0.1.0
Summary: A simple Python library that prints Hello World
Author-email: asnpoatmher <asnpoatmher@gmail.com>
Requires-Python: >=3.6
